ai_practicals/__init__.py
ai_practicals/practical_1.py
ai_practicals/practical_10.py
ai_practicals/practical_11.py
ai_practicals/practical_12.py
ai_practicals/practical_13.py
ai_practicals/practical_14.py
ai_practicals/practical_2.py
ai_practicals/practical_3.py
ai_practicals/practical_4.py
ai_practicals/practical_5.py
ai_practicals/practical_6.py
ai_practicals/practical_7.py
ai_practicals/practical_8.py
ai_practicals/practical_9.py
ai_practicals-2.0.2.dist-info/METADATA
ai_practicals-2.0.2.dist-info/WHEEL
ai_practicals-2.0.2.dist-info/entry_points.txt
ai_practicals-2.0.2.dist-info/top_level.txt
ai_practicals-2.0.2.dist-info/RECORD
